[
  {
    "platoID": 49,
    "plato": "Txistorra a la Navarra",
    "descripcion": null,
    "precio": 4.5,
    "cantidad": 2
  },
  {
    "platoID": 52,
    "plato": "Tortitas de camar\u00f3n",
    "descripcion": null,
    "precio": 4,
    "cantidad": 5
  },
  {
    "platoID": 73,
    "plato": "Pizza 3 Quesos",
    "descripcion": "tomate, queso mozzarella, queso semicurado, queso roquefort, or\u00e9gano",
    "precio": 8.2,
    "cantidad": 6
  },
  {
    "platoID": 65,
    "plato": "Canelones",
    "descripcion": null,
    "precio": 6,
    "cantidad": 1
  }
]